README.txt
buildout.cfg
setup.py
wc/__init__.py
wc.cookiecredentials.egg-info/PKG-INFO
wc.cookiecredentials.egg-info/SOURCES.txt
wc.cookiecredentials.egg-info/dependency_links.txt
wc.cookiecredentials.egg-info/namespace_packages.txt
wc.cookiecredentials.egg-info/not-zip-safe
wc.cookiecredentials.egg-info/requires.txt
wc.cookiecredentials.egg-info/top_level.txt
wc/cookiecredentials/README.txt
wc/cookiecredentials/__init__.py
wc/cookiecredentials/browser.py
wc/cookiecredentials/configure.zcml
wc/cookiecredentials/ftesting.zcml
wc/cookiecredentials/interfaces.py
wc/cookiecredentials/plugin.py
wc/cookiecredentials/tests.py
wc/cookiecredentials/wc.cookiecredentials-configure.zcml
