Metadata-Version: 1.0
Name: wc.cookiecredentials
Version: 3.9
Summary: Cookie Credentials plug-in for Zope's Pluggable Authentication Utility
Home-page: http://worldcookery.com/Downloads
Author: Philipp von Weitershausen
Author-email: philipp@weitershausen.de
License: UNKNOWN
Platform: UNKNOWN
Classifier: Development Status :: 5 - Production/Stable
Classifier: Environment :: Web Environment
Classifier: Framework :: Zope3
Classifier: Intended Audience :: Developers
